banana_bot_client/__init__.py
banana_bot_client/client.py
banana_bot_client/constants.py
banana_bot_client/encrypt.py
banana_bot_client/exceptions.py
banana_bot_client/models.py
banana_bot_client-0.1.17.dist-info/METADATA
banana_bot_client-0.1.17.dist-info/WHEEL
banana_bot_client-0.1.17.dist-info/RECORD
